<?xml version="1.0" encoding="UTF-8"?>
<gresources>
  <gresource prefix="/org/redvulps/nandu/js">
    <file>main.js</file>
    <file>window.js</file>
    <file>compose-item.js</file>
    <file>compose-detail.js</file>
    <file>container-item.js</file>
    <file>container-manager.js</file>
    <file>settings-manager.js</file>
    <file>setup-dialog.js</file>
    <file>docker/connection.js</file>
    <file>docker/client.js</file>
    <file>docker/types.js</file>
    <file>docker/container/disk-usage.js</file>
    <file>docker/container/logs.js</file>
    <file>docker/container/monitor.js</file>
    <file>docker/container/mounts.js</file>
    <file>docker/container/network.js</file>
    <file>docker/container/summary.js</file>
    <file>models/container-info.js</file>
    <file>utils/formatDate.js</file>
    <file>utils/formatBytes.js</file>
  </gresource>
</gresources>
